docsman/__init__.py
docsman/_file_util.py
docsman/badge.py
docsman/data.py
docsman/doc.py
docsman/element.py
docsman/schema.py
docsman/jsonschema/__init__.py
docsman/jsonschema/jsonschema.py
docsman/jsonschema/main.py
docsman/jsonschema/markdown.py
docsman/jsonschema/text.py
DocsMan-0.0.0.dev6.dist-info/METADATA
DocsMan-0.0.0.dev6.dist-info/WHEEL
DocsMan-0.0.0.dev6.dist-info/top_level.txt
DocsMan-0.0.0.dev6.dist-info/RECORD
