Metadata-Version: 2.1
Name: DocsMan
Version: 0.0.0.dev6
Requires-Python: >=3.10
Requires-Dist: PkgData
Requires-Dist: PyBadger
Requires-Dist: PySerials
Requires-Dist: MarkItUp
Requires-Dist: PyLinks
Requires-Dist: PyColorIt
